CHANGELOG.md
LICENSE
README.md
django_kafka/__init__.py
django_kafka/admin.py
django_kafka/apps.py
django_kafka/conf.py
django_kafka/error_handlers.py
django_kafka/exceptions.py
django_kafka/models.py
django_kafka/producer.py
django_kafka/py.typed
django_kafka/registry.py
django_kafka/serialization.py
django_kafka/connect/__init__.py
django_kafka/connect/client.py
django_kafka/connect/connector.py
django_kafka/connect/models.py
django_kafka/consumer/__init__.py
django_kafka/consumer/consumer.py
django_kafka/consumer/managers.py
django_kafka/consumer/runner.py
django_kafka/consumer/topics.py
django_kafka/dead_letter/__init__.py
django_kafka/dead_letter/header.py
django_kafka/dead_letter/topic.py
django_kafka/locale/de/LC_MESSAGES/django.po
django_kafka/management/__init__.py
django_kafka/management/commands/__init__.py
django_kafka/management/commands/errors.py
django_kafka/management/commands/kafka_connect.py
django_kafka/management/commands/kafka_consume.py
django_kafka/migrations/0001_initial.py
django_kafka/migrations/0002_waitingmessage.py
django_kafka/migrations/__init__.py
django_kafka/relations_resolver/__init__.py
django_kafka/relations_resolver/relation.py
django_kafka/relations_resolver/resolver.py
django_kafka/relations_resolver/daemon/__init__.py
django_kafka/relations_resolver/daemon/temporal.py
django_kafka/relations_resolver/processor/__init__.py
django_kafka/relations_resolver/processor/base.py
django_kafka/relations_resolver/processor/model.py
django_kafka/relations_resolver/temporalio/__init__.py
django_kafka/relations_resolver/temporalio/activities.py
django_kafka/relations_resolver/temporalio/schedules.py
django_kafka/relations_resolver/temporalio/workflows.py
django_kafka/retry/__init__.py
django_kafka/retry/consumer.py
django_kafka/retry/header.py
django_kafka/retry/settings.py
django_kafka/retry/topic.py
django_kafka/retry/tracker.py
django_kafka/tests/__init__.py
django_kafka/tests/models.py
django_kafka/tests/test_django_kafka_interface.py
django_kafka-1.0.1.dist-info/METADATA
django_kafka-1.0.1.dist-info/WHEEL
django_kafka-1.0.1.dist-info/licenses/LICENSE
django_kafka-1.0.1.dist-info/RECORD
