Metadata-Version: 2.4
Name: django-kafka
Version: 1.0.1
Summary: Confluent's Kafka Python Client combined with Django
Project-URL: Homepage, https://github.com/RegioHelden/django-kafka
Project-URL: Documentation, https://github.com/RegioHelden/django-kafka/blob/main/README.md
Project-URL: Repository, https://github.com/RegioHelden/django-kafka.git
Project-URL: Issues, https://github.com/RegioHelden/django-kafka/issues
Project-URL: Changelog, https://github.com/RegioHelden/django-kafka/blob/main/CHANGELOG.md
Author-email: RegioHelden GmbH <opensource@regiohelden.de>
Maintainer-email: RegioHelden GmbH <opensource@regiohelden.de>
License-Expression: MIT
License-File: LICENSE
Keywords: confluent,django,kafka
Classifier: Development Status :: 5 - Production/Stable
Classifier: Environment :: Web Environment
Classifier: Framework :: Django
Classifier: Intended Audience :: Developers
Classifier: License :: OSI Approved :: MIT License
Classifier: Operating System :: OS Independent
Classifier: Programming Language :: Python
Classifier: Programming Language :: Python :: 3
Classifier: Programming Language :: Python :: 3.11
Classifier: Programming Language :: Python :: 3.12
Classifier: Programming Language :: Python :: 3.13
Classifier: Topic :: Software Development
Classifier: Topic :: Software Development :: Libraries :: Python Modules
Requires-Python: >=3.11
Requires-Dist: confluent-kafka[avro,schemaregistry]>=2.9.0
Requires-Dist: django-temporalio>=1.4.0
Requires-Dist: django<6.1,>=4.2
